having_a_sip/__init__.py
having_a_sip/file_utils.py
having_a_sip-0.0.2.dist-info/METADATA
having_a_sip-0.0.2.dist-info/WHEEL
having_a_sip-0.0.2.dist-info/top_level.txt
having_a_sip-0.0.2.dist-info/RECORD
